WebNMS-1b1.data/data/LICENSE.txt
WebNMS-1b1.dist-info/METADATA
WebNMS-1b1.dist-info/RECORD
WebNMS-1b1.dist-info/WHEEL
WebNMS-1b1.dist-info/top_level.txt
webnms/__init__.py
webnms/edge.py
